<?xml version="1.0" encoding="utf-8" ?>
<dwsync>
<file name="auth.php" server="192.186.236.99" local="132162468270561532" remote="132162499800000000" Dst="2" />
<file name="app.php" server="192.186.236.99" local="132162468270551555" remote="132162499800000000" Dst="2" />
<file name="broadcasting.php" server="192.186.236.99" local="132162468270566543" remote="132162499800000000" Dst="2" />
<file name="cache.php" server="192.186.236.99" local="132162468270576528" remote="132162499800000000" Dst="2" />
<file name="database.php" server="192.186.236.99" local="132162468270591557" remote="132162499800000000" Dst="2" />
<file name="filesystems.php" server="192.186.236.99" local="132162468270606554" remote="132162499800000000" Dst="2" />
<file name="hashing.php" server="192.186.236.99" local="132162468270611533" remote="132162499800000000" Dst="2" />
<file name="logging.php" server="192.186.236.99" local="132162468270621536" remote="132162499800000000" Dst="2" />
<file name="mail.php" server="192.186.236.99" local="132162468270631542" remote="132162499800000000" Dst="2" />
<file name="queue.php" server="192.186.236.99" local="132162468270636542" remote="132162499800000000" Dst="2" />
<file name="services.php" server="192.186.236.99" local="132162468270646527" remote="132162499800000000" Dst="2" />
<file name="session.php" server="192.186.236.99" local="132162468270651559" remote="132162499800000000" Dst="2" />
<file name="view.php" server="192.186.236.99" local="132162468270656530" remote="132162499800000000" Dst="2" />
</dwsync>