{"49":{"score":657},"227":{"score":579},"63":{"score":446},"189":{"score":346},"44":{"score":334},"21":{"score":332},"4":{"score":306},"183":{"score":305},"166":{"score":297},"41":{"score":297},"5":{"score":295},"35":{"score":285},"139":{"score":280},"6":{"score":280},"158":{"score":276},"118":{"score":262},"187":{"score":262},"29":{"score":260},"28":{"score":259},"13":{"score":258},"156":{"score":256},"36":{"score":252},"82":{"score":252},"18":{"score":250},"51":{"score":245},"154":{"score":244},"7":{"score":235},"173":{"score":230},"61":{"score":228},"45":{"score":226},"213":{"score":226},"136":{"score":225},"155":{"score":222},"24":{"score":219},"19":{"score":219},"167":{"score":215},"130":{"score":212},"186":{"score":212},"52":{"score":211},"33":{"score":210},"180":{"score":208},"145":{"score":208},"127":{"score":208},"164":{"score":208},"109":{"score":208},"152":{"score":205},"22":{"score":203},"129":{"score":201},"215":{"score":200},"15":{"score":198},"116":{"score":197},"71":{"score":195},"40":{"score":191},"32":{"score":190},"10":{"score":190},"16":{"score":190},"53":{"score":188},"119":{"score":188},"83":{"score":186},"135":{"score":183},"84":{"score":180},"38":{"score":178},"184":{"score":178},"182":{"score":178},"93":{"score":177},"202":{"score":176},"27":{"score":176},"142":{"score":175},"74":{"score":174},"216":{"score":174},"174":{"score":172},"200":{"score":172},"67":{"score":172},"148":{"score":172},"103":{"score":172},"190":{"score":172},"121":{"score":172},"8":{"score":172},"221":{"score":169},"197":{"score":168},"211":{"score":168},"223":{"score":168},"113":{"score":167},"3":{"score":167},"161":{"score":166},"149":{"score":166},"124":{"score":161},"157":{"score":161},"14":{"score":160},"106":{"score":159},"122":{"score":158},"128":{"score":158},"140":{"score":158},"175":{"score":158},"104":{"score":158},"191":{"score":158},"159":{"score":158},"198":{"score":158},"9":{"score":158},"68":{"score":158},"31":{"score":157},"85":{"score":157},"70":{"score":156},"120":{"score":156},"217":{"score":156},"34":{"score":156},"181":{"score":155},"201":{"score":153},"91":{"score":153},"176":{"score":152},"75":{"score":150},"72":{"score":150},"132":{"score":149},"79":{"score":149},"87":{"score":147},"46":{"score":146},"57":{"score":146},"214":{"score":146},"59":{"score":145},"80":{"score":144},"160":{"score":144},"177":{"score":144},"65":{"score":143},"210":{"score":142},"86":{"score":142},"199":{"score":140},"171":{"score":140},"224":{"score":139},"204":{"score":139},"94":{"score":139},"92":{"score":139},"111":{"score":138},"141":{"score":138},"96":{"score":137},"20":{"score":137},"105":{"score":137},"39":{"score":136},"81":{"score":135},"78":{"score":134},"42":{"score":134},"151":{"score":134},"30":{"score":134},"206":{"score":133},"50":{"score":133},"12":{"score":133},"62":{"score":132},"194":{"score":132},"219":{"score":132},"203":{"score":130},"90":{"score":130},"43":{"score":130},"208":{"score":130},"207":{"score":129},"222":{"score":128},"225":{"score":125},"95":{"score":125},"66":{"score":124},"102":{"score":124},"25":{"score":123},"26":{"score":121},"212":{"score":121},"77":{"score":120},"37":{"score":120},"64":{"score":119},"170":{"score":118},"60":{"score":118},"98":{"score":117},"218":{"score":117},"112":{"score":117},"123":{"score":117},"126":{"score":115},"23":{"score":115},"163":{"score":115},"108":{"score":115},"110":{"score":115},"150":{"score":115},"144":{"score":115},"179":{"score":115},"131":{"score":115},"73":{"score":113},"205":{"score":112},"192":{"score":111},"117":{"score":111},"165":{"score":111},"185":{"score":111},"153":{"score":111},"54":{"score":111},"97":{"score":111},"169":{"score":110},"188":{"score":110},"146":{"score":108},"11":{"score":107},"226":{"score":104},"56":{"score":104},"209":{"score":103},"114":{"score":103},"58":{"score":103},"172":{"score":102},"17":{"score":101},"76":{"score":100},"2":{"score":99},"101":{"score":98},"55":{"score":98},"69":{"score":98},"196":{"score":98},"89":{"score":97},"168":{"score":97},"193":{"score":96},"138":{"score":94},"99":{"score":90},"133":{"score":90},"220":{"score":90},"137":{"score":89},"47":{"score":88},"195":{"score":87},"88":{"score":87},"100":{"score":86},"147":{"score":83},"48":{"score":70},"178":{"score":70},"125":{"score":70},"162":{"score":70},"143":{"score":70},"107":{"score":70},"115":{"score":69},"134":{"score":69},"1":{"score":45}}